.DS_Store
icheckin/__init__.py
icheckin/commands.py
icheckin/connections.py
icheckin/constants.py
icheckin/credentials.py
icheckin/icheckin.py
icheckin/commands/__init__.py
icheckin/commands/add.py
icheckin/commands/clear.py
icheckin/commands/code.py
icheckin/commands/remove.py
icheckin/commands/save.py
icheckin/commands/show.py
icheckin/commands/update.py
icheckin-1.3.5.dist-info/DESCRIPTION.rst
icheckin-1.3.5.dist-info/METADATA
icheckin-1.3.5.dist-info/RECORD
icheckin-1.3.5.dist-info/WHEEL
icheckin-1.3.5.dist-info/entry_points.txt
icheckin-1.3.5.dist-info/metadata.json
icheckin-1.3.5.dist-info/top_level.txt
test/__init__.py
test/test_icheckin.py
